khive/__init__.py
khive/_types.py
khive/py.typed
khive/utils.py
khive/cli/__init__.py
khive/cli/base.py
khive/cli/khive_claude.py
khive/cli/khive_clean.py
khive/cli/khive_cli.py
khive/cli/khive_commit.py
khive/cli/khive_mcp.py
khive/cli/khive_new_doc.py
khive/cli/khive_pr.py
khive/cli/commands/__init__.py
khive/cli/commands/claude.py
khive/cli/commands/clean.py
khive/cli/commands/commit.py
khive/cli/commands/compose.py
khive/cli/commands/mcp.py
khive/cli/commands/new_doc.py
khive/cli/commands/plan.py
khive/cli/commands/pr.py
khive/cli/commands/session.py
khive/prompts/__init__.py
khive/prompts/agent_prompts.yaml
khive/prompts/decision_matrix.yaml
khive/prompts/name_mapper.yaml
khive/prompts/domains/__init__.py
khive/prompts/domains/architecture/hierarchical-clustering.yaml
khive/prompts/domains/architecture/microservices-architecture.yaml
khive/prompts/domains/architecture/nextjs.yaml
khive/prompts/domains/architecture/software-architecture.yaml
khive/prompts/domains/engineering/api-design.yaml
khive/prompts/domains/engineering/async-programming.yaml
khive/prompts/domains/engineering/backend-development.yaml
khive/prompts/domains/engineering/database-design.yaml
khive/prompts/domains/engineering/frontend-development.yaml
khive/prompts/domains/engineering/protocol-design.yaml
khive/prompts/domains/engineering/rust.yaml
khive/prompts/domains/engineering/typescript.yaml
khive/prompts/domains/operations/agile-methodology.yaml
khive/prompts/domains/operations/ai-governance.yaml
khive/prompts/domains/operations/ci-cd-pipelines.yaml
khive/prompts/domains/operations/code-quality.yaml
khive/prompts/domains/operations/devops-automation.yaml
khive/prompts/gates/__init__.py
khive/prompts/gates/design.py
khive/prompts/gates/documentation.py
khive/prompts/gates/factory.py
khive/prompts/gates/performance.py
khive/prompts/gates/security.py
khive/prompts/gates/testing.py
khive/prompts/roles/README.md
khive/prompts/roles/__init__.py
khive/prompts/roles/analyst.md
khive-0.4.0.dist-info/METADATA
khive-0.4.0.dist-info/WHEEL
khive-0.4.0.dist-info/entry_points.txt
khive-0.4.0.dist-info/licenses/LICENSE
khive-0.4.0.dist-info/RECORD
