Metadata-Version: 2.4
Name: khive
Version: 0.4.0
Summary: Add your description here
License-File: LICENSE
Requires-Python: >=3.10
Requires-Dist: aiofiles>=24.1.0
Requires-Dist: fastmcp>=2.11.3
Requires-Dist: lionagi[graph,postgres,rich,schema,sqlite]>=0.15.7
Requires-Dist: nest-asyncio>=1.6.0
Requires-Dist: openai>=1.99.9
Requires-Dist: plotly>=6.3.0
Requires-Dist: pydantic-settings>=2.10.1
Requires-Dist: pyyaml>=6.0.2
Requires-Dist: streamlit>=1.48.1
Requires-Dist: tenacity>=9.1.2
Requires-Dist: websockets>=15.0.1
